iterfast/__init__.py
iterfast-0.0.4.dist-info/LICENSE
iterfast-0.0.4.dist-info/METADATA
iterfast-0.0.4.dist-info/WHEEL
iterfast-0.0.4.dist-info/top_level.txt
iterfast-0.0.4.dist-info/RECORD
